atcoder/__init__.py
atcoder/__main__.py
atcoder/auth.py
atcoder/constant.py
atcoder/contest.py
atcoder/crawl.py
atcoder/editorial.py
atcoder/home.py
atcoder/language.py
atcoder/login.py
atcoder/network.py
atcoder/score.py
atcoder/scrape.py
atcoder/standings.py
atcoder/submission.py
atcoder/submit.py
atcoder/task.py
atcoder/top.py
atcoder/user.py
atcoder/user_agent.py
src/languages.yaml
atcoder-0.1.3.dist-info/LICENSE
atcoder-0.1.3.dist-info/WHEEL
atcoder-0.1.3.dist-info/METADATA
atcoder-0.1.3.dist-info/RECORD
