Metadata-Version: 2.1
Name: atcoder
Version: 0.1.3
Summary: AtCoder API for Python
Home-page: https://kagemeka.github.io/atcoder-python
License: MIT
Keywords: atcoder,api
Author: Hiroshi Tsuyuki
Author-email: kagemeka1@gmail.com
Maintainer: Hiroshi Tsuyuki
Maintainer-email: kagemeka1@gmail.com
Requires-Python: >=3.8,<3.11
Classifier: License :: OSI Approved :: MIT License
Classifier: Programming Language :: Python :: 3
Classifier: Programming Language :: Python :: 3.10
Classifier: Programming Language :: Python :: 3.8
Classifier: Programming Language :: Python :: 3.9
Provides-Extra: docs
Requires-Dist: PyYAML
Requires-Dist: aiodns
Requires-Dist: aiohttp
Requires-Dist: beautifulsoup4
Requires-Dist: cchardet
Requires-Dist: filesystem-python (==0.2.0)
Requires-Dist: furo; extra == "docs"
Requires-Dist: lxml
Requires-Dist: myst-parser; extra == "docs"
Requires-Dist: optext-python (==0.1.1)
Requires-Dist: pandas
Requires-Dist: pdoc3; extra == "docs"
Requires-Dist: pydata-sphinx-theme; extra == "docs"
Requires-Dist: python-docs-theme; extra == "docs"
Requires-Dist: requests
Requires-Dist: selenium
Requires-Dist: sphinx-book-theme; extra == "docs"
Requires-Dist: sphinx-theme-pd; extra == "docs"
Requires-Dist: sphinx; extra == "docs"
Requires-Dist: sphinx_rtd_theme (<=2.0.0); extra == "docs"
Requires-Dist: sphinxcontrib-mermaid; extra == "docs"
Requires-Dist: tqdm
Project-URL: Documentation, https://atcoder-python.readthedocs.io
Project-URL: Repository, https://github.com/kagemeka/atcoder-python
